{
"meta":{"test_sets":[],"test_metrics":[],"learn_metrics":[{"best_value":"Min","name":"Logloss"}],"launch_mode":"Train","parameters":"","iteration_count":250,"learn_sets":["learn"],"name":"experiment"},
"iterations":[
{"learn":[0.6851144937],"iteration":0,"passed_time":0.002714321465,"remaining_time":0.6758660448},
{"learn":[0.6781693972],"iteration":1,"passed_time":0.003896702435,"remaining_time":0.483191102},
{"learn":[0.6711475666],"iteration":2,"passed_time":0.005174690037,"remaining_time":0.4260494797},
{"learn":[0.6638788077],"iteration":3,"passed_time":0.006288175968,"remaining_time":0.386722822},
{"learn":[0.6583071489],"iteration":4,"passed_time":0.007327528093,"remaining_time":0.3590488766},
{"learn":[0.6507666661],"iteration":5,"passed_time":0.008483110808,"remaining_time":0.3449798395},
{"learn":[0.6438256777],"iteration":6,"passed_time":0.009661618536,"remaining_time":0.3353961863},
{"learn":[0.6367546962],"iteration":7,"passed_time":0.01079316515,"remaining_time":0.3264932458},
{"learn":[0.6314204289],"iteration":8,"passed_time":0.011773672,"remaining_time":0.3152727724},
{"learn":[0.6246050321],"iteration":9,"passed_time":0.01271966522,"remaining_time":0.3052719652},
{"learn":[0.6188559165],"iteration":10,"passed_time":0.0137225882,"remaining_time":0.2981544164},
{"learn":[0.6125685985],"iteration":11,"passed_time":0.01481646015,"remaining_time":0.293859793},
{"learn":[0.6081136924],"iteration":12,"passed_time":0.01591720083,"remaining_time":0.2901828151},
{"learn":[0.6029043931],"iteration":13,"passed_time":0.01762199058,"remaining_time":0.2970564126},
{"learn":[0.5976957908],"iteration":14,"passed_time":0.01908755708,"remaining_time":0.2990383943},
{"learn":[0.593046005],"iteration":15,"passed_time":0.02036072591,"remaining_time":0.2977756164},
{"learn":[0.5867146712],"iteration":16,"passed_time":0.02146047328,"remaining_time":0.2941347219},
{"learn":[0.5810552744],"iteration":17,"passed_time":0.02252903249,"remaining_time":0.2903741965},
{"learn":[0.5740114359],"iteration":18,"passed_time":0.02357050345,"remaining_time":0.2865676999},
{"learn":[0.5687212577],"iteration":19,"passed_time":0.02461370104,"remaining_time":0.283057562},
{"learn":[0.5634371684],"iteration":20,"passed_time":0.02557491168,"remaining_time":0.2788883226},
{"learn":[0.5580196381],"iteration":21,"passed_time":0.02660983724,"remaining_time":0.2757746769},
{"learn":[0.5540630267],"iteration":22,"passed_time":0.02761936674,"remaining_time":0.2725911413},
{"learn":[0.5476668431],"iteration":23,"passed_time":0.0286139477,"remaining_time":0.2694480075},
{"learn":[0.5425121601],"iteration":24,"passed_time":0.02975925621,"remaining_time":0.2678333059},
{"learn":[0.538198141],"iteration":25,"passed_time":0.03239386623,"remaining_time":0.2790856167},
{"learn":[0.5337702311],"iteration":26,"passed_time":0.03343635606,"remaining_time":0.2761595334},
{"learn":[0.5283465019],"iteration":27,"passed_time":0.03501516322,"remaining_time":0.2776202227},
{"learn":[0.5235337477],"iteration":28,"passed_time":0.03607031609,"remaining_time":0.2748806846},
{"learn":[0.5185239498],"iteration":29,"passed_time":0.03709213862,"remaining_time":0.2720090166},
{"learn":[0.5129704109],"iteration":30,"passed_time":0.03810496138,"remaining_time":0.2691931142},
{"learn":[0.5080834169],"iteration":31,"passed_time":0.03908486268,"remaining_time":0.266265627},
{"learn":[0.5037016502],"iteration":32,"passed_time":0.03988165276,"remaining_time":0.2622520803},
{"learn":[0.4997787476],"iteration":33,"passed_time":0.04098964104,"remaining_time":0.2604047784},
{"learn":[0.4956691449],"iteration":34,"passed_time":0.04201790898,"remaining_time":0.2581100123},
{"learn":[0.4919635333],"iteration":35,"passed_time":0.04297246311,"remaining_time":0.2554474196},
{"learn":[0.4885978699],"iteration":36,"passed_time":0.04410976515,"remaining_time":0.2539291885},
{"learn":[0.4840770868],"iteration":37,"passed_time":0.04512308233,"remaining_time":0.2517393014},
{"learn":[0.4796799513],"iteration":38,"passed_time":0.04748002112,"remaining_time":0.2568790886},
{"learn":[0.475418531],"iteration":39,"passed_time":0.04858336063,"remaining_time":0.2550626433},
{"learn":[0.4712298467],"iteration":40,"passed_time":0.04983921097,"remaining_time":0.2540584169},
{"learn":[0.4679274926],"iteration":41,"passed_time":0.0510968535,"remaining_time":0.253051084},
{"learn":[0.4640858724],"iteration":42,"passed_time":0.05218811773,"remaining_time":0.2512311714},
{"learn":[0.4601631898],"iteration":43,"passed_time":0.0532107347,"remaining_time":0.2491229852},
{"learn":[0.4565820327],"iteration":44,"passed_time":0.05420389014,"remaining_time":0.2469288328},
{"learn":[0.4518644993],"iteration":45,"passed_time":0.05516886735,"remaining_time":0.2446619335},
{"learn":[0.4483408194],"iteration":46,"passed_time":0.05613400567,"remaining_time":0.2424511309},
{"learn":[0.4457151706],"iteration":47,"passed_time":0.05715986479,"remaining_time":0.2405477643},
{"learn":[0.4428937252],"iteration":48,"passed_time":0.05820949111,"remaining_time":0.2387777084},
{"learn":[0.4393325952],"iteration":49,"passed_time":0.0592144996,"remaining_time":0.2368579984},
{"learn":[0.4358569659],"iteration":50,"passed_time":0.06036459245,"remaining_time":0.2355402725},
{"learn":[0.4313557698],"iteration":51,"passed_time":0.06337834573,"remaining_time":0.2413252395},
{"learn":[0.4281256015],"iteration":52,"passed_time":0.0646868215,"remaining_time":0.240439695},
{"learn":[0.424645644],"iteration":53,"passed_time":0.06603045089,"remaining_time":0.239666081},
{"learn":[0.4210362801],"iteration":54,"passed_time":0.06728851674,"remaining_time":0.2385683775},
{"learn":[0.4179487962],"iteration":55,"passed_time":0.06833255542,"remaining_time":0.2367234956},
{"learn":[0.4146655156],"iteration":56,"passed_time":0.0693026114,"remaining_time":0.2346562105},
{"learn":[0.4118806399],"iteration":57,"passed_time":0.07035146331,"remaining_time":0.2328876027},
{"learn":[0.4097724328],"iteration":58,"passed_time":0.07136355385,"remaining_time":0.2310243862},
{"learn":[0.4068201505],"iteration":59,"passed_time":0.07236622351,"remaining_time":0.2291597078},
{"learn":[0.4028292436],"iteration":60,"passed_time":0.07347634841,"remaining_time":0.227656227},
{"learn":[0.3991300143],"iteration":61,"passed_time":0.07443526466,"remaining_time":0.2257069315},
{"learn":[0.3964881897],"iteration":62,"passed_time":0.07667343959,"remaining_time":0.2275862413},
{"learn":[0.3935987032],"iteration":63,"passed_time":0.0779585048,"remaining_time":0.2265669046},
{"learn":[0.3910008577],"iteration":64,"passed_time":0.0792948888,"remaining_time":0.2256854527},
{"learn":[0.3897851797],"iteration":65,"passed_time":0.0799066088,"remaining_time":0.2227699397},
{"learn":[0.3870901328],"iteration":66,"passed_time":0.08099696305,"remaining_time":0.221230511},
{"learn":[0.3839258781],"iteration":67,"passed_time":0.08198501528,"remaining_time":0.2194304821},
{"learn":[0.3820359523],"iteration":68,"passed_time":0.08298885491,"remaining_time":0.217695402},
{"learn":[0.3793084071],"iteration":69,"passed_time":0.08398791688,"remaining_time":0.2159689291},
{"learn":[0.3759739949],"iteration":70,"passed_time":0.08509524406,"remaining_time":0.214535897},
{"learn":[0.3737089451],"iteration":71,"passed_time":0.08608300519,"remaining_time":0.2128163184},
{"learn":[0.3705014449],"iteration":72,"passed_time":0.08727630256,"remaining_time":0.2116151446},
{"learn":[0.3682001921],"iteration":73,"passed_time":0.08844918265,"remaining_time":0.2103656236},
{"learn":[0.365338839],"iteration":74,"passed_time":0.0895055777,"remaining_time":0.208846348},
{"learn":[0.3620166779],"iteration":75,"passed_time":0.0931583859,"remaining_time":0.213283673},
{"learn":[0.3593323414],"iteration":76,"passed_time":0.09440203876,"remaining_time":0.2120980871},
{"learn":[0.357384535],"iteration":77,"passed_time":0.09570758126,"remaining_time":0.2110474869},
{"learn":[0.3551929547],"iteration":78,"passed_time":0.09668651037,"remaining_time":0.2092834592},
{"learn":[0.353004749],"iteration":79,"passed_time":0.0976615629,"remaining_time":0.2075308212},
{"learn":[0.3502407074],"iteration":80,"passed_time":0.09877796876,"remaining_time":0.2060923052},
{"learn":[0.3482819704],"iteration":81,"passed_time":0.09989148136,"remaining_time":0.2046557179},
{"learn":[0.345449521],"iteration":82,"passed_time":0.100965826,"remaining_time":0.2031481077},
{"learn":[0.3431489651],"iteration":83,"passed_time":0.1020018226,"remaining_time":0.2015750305},
{"learn":[0.3411616912],"iteration":84,"passed_time":0.1030123532,"remaining_time":0.1999651563},
{"learn":[0.3389976942],"iteration":85,"passed_time":0.1039583109,"remaining_time":0.1982460812},
{"learn":[0.3361713703],"iteration":86,"passed_time":0.1070075933,"remaining_time":0.200485491},
{"learn":[0.3337093133],"iteration":87,"passed_time":0.1080878189,"remaining_time":0.1989798485},
{"learn":[0.3316040039],"iteration":88,"passed_time":0.1093328851,"remaining_time":0.1977819607},
{"learn":[0.32903873],"iteration":89,"passed_time":0.1104189772,"remaining_time":0.196300404},
{"learn":[0.3267170466],"iteration":90,"passed_time":0.1114672003,"remaining_time":0.1947613719},
{"learn":[0.3240671525],"iteration":91,"passed_time":0.1126200897,"remaining_time":0.1934127627},
{"learn":[0.3222561249],"iteration":92,"passed_time":0.1137955864,"remaining_time":0.1921065276},
{"learn":[0.3204032458],"iteration":93,"passed_time":0.114805567,"remaining_time":0.1905283878},
{"learn":[0.3183711859],"iteration":94,"passed_time":0.115893678,"remaining_time":0.1890896851},
{"learn":[0.3169513116],"iteration":95,"passed_time":0.1168828368,"remaining_time":0.1874995507},
{"learn":[0.3147040881],"iteration":96,"passed_time":0.1179035961,"remaining_time":0.1859716515},
{"learn":[0.3122602609],"iteration":97,"passed_time":0.1188511604,"remaining_time":0.1843405752},
{"learn":[0.3099554502],"iteration":98,"passed_time":0.1203301299,"remaining_time":0.1835338345},
{"learn":[0.3078354322],"iteration":99,"passed_time":0.1219783265,"remaining_time":0.1829674898},
{"learn":[0.306120469],"iteration":100,"passed_time":0.1230177942,"remaining_time":0.1814816964},
{"learn":[0.3037267098],"iteration":101,"passed_time":0.1242982773,"remaining_time":0.1803543631},
{"learn":[0.3023646611],"iteration":102,"passed_time":0.1252692499,"remaining_time":0.1787823276},
{"learn":[0.2999478303],"iteration":103,"passed_time":0.1263264227,"remaining_time":0.1773428627},
{"learn":[0.2979910557],"iteration":104,"passed_time":0.1274325355,"remaining_time":0.1759782633},
{"learn":[0.2965574265],"iteration":105,"passed_time":0.1285378994,"remaining_time":0.1746175237},
{"learn":[0.2948323397],"iteration":106,"passed_time":0.1296250448,"remaining_time":0.1732372095},
{"learn":[0.292421561],"iteration":107,"passed_time":0.1308056336,"remaining_time":0.171985185},
{"learn":[0.2907313567],"iteration":108,"passed_time":0.1317816384,"remaining_time":0.1704698258},
{"learn":[0.2888814853],"iteration":109,"passed_time":0.1328646917,"remaining_time":0.1691005167},
{"learn":[0.2877659614],"iteration":110,"passed_time":0.1338549405,"remaining_time":0.1676201508},
{"learn":[0.2863503053],"iteration":111,"passed_time":0.1362723001,"remaining_time":0.1679069412},
{"learn":[0.2848956952],"iteration":112,"passed_time":0.1373129433,"remaining_time":0.1664767543},
{"learn":[0.2834802591],"iteration":113,"passed_time":0.1383690539,"remaining_time":0.1650718538},
{"learn":[0.2816355412],"iteration":114,"passed_time":0.1395882818,"remaining_time":0.1638645047},
{"learn":[0.2803727663],"iteration":115,"passed_time":0.1408447433,"remaining_time":0.162699962},
{"learn":[0.2786127054],"iteration":116,"passed_time":0.1418605804,"remaining_time":0.1612603179},
{"learn":[0.2764558242],"iteration":117,"passed_time":0.1429893571,"remaining_time":0.159954196},
{"learn":[0.2752000002],"iteration":118,"passed_time":0.1440754314,"remaining_time":0.1586040464},
{"learn":[0.2733380244],"iteration":119,"passed_time":0.1453036435,"remaining_time":0.1574122805},
{"learn":[0.2721615938],"iteration":120,"passed_time":0.1464433688,"remaining_time":0.156125575},
{"learn":[0.2700501955],"iteration":121,"passed_time":0.1474638192,"remaining_time":0.1547161382},
{"learn":[0.2685616567],"iteration":122,"passed_time":0.1484520059,"remaining_time":0.1532797134},
{"learn":[0.266686953],"iteration":123,"passed_time":0.1505706647,"remaining_time":0.1529992238},
{"learn":[0.2651049907],"iteration":124,"passed_time":0.1520202705,"remaining_time":0.1520202705},
{"learn":[0.2632372196],"iteration":125,"passed_time":0.1531543571,"remaining_time":0.1507233355},
{"learn":[0.2619657883],"iteration":126,"passed_time":0.1544174828,"remaining_time":0.14955394},
{"learn":[0.260360516],"iteration":127,"passed_time":0.1555201567,"remaining_time":0.1482301494},
{"learn":[0.2586673223],"iteration":128,"passed_time":0.1565346206,"remaining_time":0.1468270472},
{"learn":[0.2570542922],"iteration":129,"passed_time":0.157601492,"remaining_time":0.1454783003},
{"learn":[0.256085946],"iteration":130,"passed_time":0.1586781,"remaining_time":0.1441427015},
{"learn":[0.2539271758],"iteration":131,"passed_time":0.1596959637,"remaining_time":0.142758513},
{"learn":[0.2522914226],"iteration":132,"passed_time":0.160847251,"remaining_time":0.1414972057},
{"learn":[0.2506449223],"iteration":133,"passed_time":0.1618215091,"remaining_time":0.1400842914},
{"learn":[0.2494049439],"iteration":134,"passed_time":0.1628130423,"remaining_time":0.1386925916},
{"learn":[0.2476191521],"iteration":135,"passed_time":0.1638191663,"remaining_time":0.1373190071},
{"learn":[0.2464355139],"iteration":136,"passed_time":0.1658301389,"remaining_time":0.1367796036},
{"learn":[0.2443646468],"iteration":137,"passed_time":0.1670091632,"remaining_time":0.1355436687},
{"learn":[0.2430675947],"iteration":138,"passed_time":0.1680159895,"remaining_time":0.134171042},
{"learn":[0.2418597111],"iteration":139,"passed_time":0.1694316772,"remaining_time":0.1331248892},
{"learn":[0.2404740407],"iteration":140,"passed_time":0.1704609795,"remaining_time":0.1317747998},
{"learn":[0.2391766401],"iteration":141,"passed_time":0.1714250456,"remaining_time":0.1303796122},
{"learn":[0.237972718],"iteration":142,"passed_time":0.1723670134,"remaining_time":0.1289739191},
{"learn":[0.2364637302],"iteration":143,"passed_time":0.173400719,"remaining_time":0.1276421959},
{"learn":[0.2357059625],"iteration":144,"passed_time":0.1744281125,"remaining_time":0.1263100125},
{"learn":[0.234468185],"iteration":145,"passed_time":0.1753926497,"remaining_time":0.12493723},
{"learn":[0.2330711805],"iteration":146,"passed_time":0.1764356518,"remaining_time":0.1236249805},
{"learn":[0.2317598416],"iteration":147,"passed_time":0.1774417658,"remaining_time":0.1222909467},
{"learn":[0.2305851533],"iteration":148,"passed_time":0.1785031996,"remaining_time":0.1209988132},
{"learn":[0.2291839673],"iteration":149,"passed_time":0.1796464926,"remaining_time":0.1197643284},
{"learn":[0.2282571793],"iteration":150,"passed_time":0.1828752008,"remaining_time":0.1198983105},
{"learn":[0.2268609267],"iteration":151,"passed_time":0.1841760435,"remaining_time":0.1187450806},
{"learn":[0.2259057118],"iteration":152,"passed_time":0.1851474439,"remaining_time":0.1173810592},
{"learn":[0.2244884418],"iteration":153,"passed_time":0.1861810783,"remaining_time":0.1160609319},
{"learn":[0.2229749606],"iteration":154,"passed_time":0.1871883834,"remaining_time":0.114728364},
{"learn":[0.2219723005],"iteration":155,"passed_time":0.1881397776,"remaining_time":0.1133662763},
{"learn":[0.2210496206],"iteration":156,"passed_time":0.1892020459,"remaining_time":0.1120750972},
{"learn":[0.2201457024],"iteration":157,"passed_time":0.1902553155,"remaining_time":0.1107815761},
{"learn":[0.2190902233],"iteration":158,"passed_time":0.1912339479,"remaining_time":0.1094483601},
{"learn":[0.2182342089],"iteration":159,"passed_time":0.1923001994,"remaining_time":0.1081688622},
{"learn":[0.2169362031],"iteration":160,"passed_time":0.1933272918,"remaining_time":0.1068703663},
{"learn":[0.216266302],"iteration":161,"passed_time":0.1944133595,"remaining_time":0.105607257},
{"learn":[0.2147152791],"iteration":162,"passed_time":0.1972290964,"remaining_time":0.1052695177},
{"learn":[0.2136606987],"iteration":163,"passed_time":0.1982961956,"remaining_time":0.1039845904},
{"learn":[0.2124868356],"iteration":164,"passed_time":0.1995617279,"remaining_time":0.1028045265},
{"learn":[0.2112746055],"iteration":165,"passed_time":0.2006207641,"remaining_time":0.1015189408},
{"learn":[0.2100136097],"iteration":166,"passed_time":0.2017217847,"remaining_time":0.1002569349},
{"learn":[0.2092322386],"iteration":167,"passed_time":0.202787824,"remaining_time":0.09897977124},
{"learn":[0.2082417378],"iteration":168,"passed_time":0.2038410013,"remaining_time":0.09769894147},
{"learn":[0.2073176091],"iteration":169,"passed_time":0.2049321734,"remaining_time":0.09643866982},
{"learn":[0.2063997709],"iteration":170,"passed_time":0.2060447071,"remaining_time":0.0951902448},
{"learn":[0.2054883884],"iteration":171,"passed_time":0.2070847014,"remaining_time":0.09391050413},
{"learn":[0.2044429779],"iteration":172,"passed_time":0.2081659892,"remaining_time":0.09265191428},
{"learn":[0.2035353],"iteration":173,"passed_time":0.2092030225,"remaining_time":0.09137603282},
{"learn":[0.2024160165],"iteration":174,"passed_time":0.2111343636,"remaining_time":0.09048615582},
{"learn":[0.2015872185],"iteration":175,"passed_time":0.2124658044,"remaining_time":0.0893322132},
{"learn":[0.2004182522],"iteration":176,"passed_time":0.21354617,"remaining_time":0.08807271417},
{"learn":[0.1996134428],"iteration":177,"passed_time":0.2147513393,"remaining_time":0.08686571027},
{"learn":[0.1982299731],"iteration":178,"passed_time":0.2158982289,"remaining_time":0.08563561034},
{"learn":[0.1971495702],"iteration":179,"passed_time":0.2169037685,"remaining_time":0.08435146551},
{"learn":[0.1963867041],"iteration":180,"passed_time":0.2179353897,"remaining_time":0.08308034192},
{"learn":[0.1957092285],"iteration":181,"passed_time":0.2189618099,"remaining_time":0.08180990699},
{"learn":[0.1945881477],"iteration":182,"passed_time":0.2199972899,"remaining_time":0.08054545585},
{"learn":[0.193829298],"iteration":183,"passed_time":0.2211701022,"remaining_time":0.07933275404},
{"learn":[0.1929767682],"iteration":184,"passed_time":0.2222161553,"remaining_time":0.07807594644},
{"learn":[0.1919809305],"iteration":185,"passed_time":0.2233163493,"remaining_time":0.07684003416},
{"learn":[0.1909116231],"iteration":186,"passed_time":0.2244026214,"remaining_time":0.07560088315},
{"learn":[0.1899871093],"iteration":187,"passed_time":0.2266462429,"remaining_time":0.07474503754},
{"learn":[0.1888248187],"iteration":188,"passed_time":0.227860602,"remaining_time":0.07354231069},
{"learn":[0.1877534756],"iteration":189,"passed_time":0.2290041683,"remaining_time":0.07231710578},
{"learn":[0.18688013],"iteration":190,"passed_time":0.2300822429,"remaining_time":0.07107252528},
{"learn":[0.1859546075],"iteration":191,"passed_time":0.2311758448,"remaining_time":0.06983436979},
{"learn":[0.1852767651],"iteration":192,"passed_time":0.232165467,"remaining_time":0.06856700321},
{"learn":[0.1841226174],"iteration":193,"passed_time":0.2333634243,"remaining_time":0.06736263793},
{"learn":[0.1832529948],"iteration":194,"passed_time":0.2344486264,"remaining_time":0.06612653566},
{"learn":[0.1822980734],"iteration":195,"passed_time":0.2354681001,"remaining_time":0.06487386432},
{"learn":[0.1813464532],"iteration":196,"passed_time":0.236516742,"remaining_time":0.06363140775},
{"learn":[0.180268251],"iteration":197,"passed_time":0.2375988043,"remaining_time":0.06239968597},
{"learn":[0.1794215349],"iteration":198,"passed_time":0.2385128905,"remaining_time":0.06112641916},
{"learn":[0.1786031356],"iteration":199,"passed_time":0.2395571725,"remaining_time":0.05988929312},
{"learn":[0.1776414284],"iteration":200,"passed_time":0.241831311,"remaining_time":0.05895390168},
{"learn":[0.1767366483],"iteration":201,"passed_time":0.2429517179,"remaining_time":0.05773110128},
{"learn":[0.1760176695],"iteration":202,"passed_time":0.2440840589,"remaining_time":0.05651207275},
{"learn":[0.1751263325],"iteration":203,"passed_time":0.2452516391,"remaining_time":0.05530184019},
{"learn":[0.1742090445],"iteration":204,"passed_time":0.2463258538,"remaining_time":0.05407152887},
{"learn":[0.1732369203],"iteration":205,"passed_time":0.2473609782,"remaining_time":0.05283438369},
{"learn":[0.1725938504],"iteration":206,"passed_time":0.2484104668,"remaining_time":0.05160217425},
{"learn":[0.1717706827],"iteration":207,"passed_time":0.2494976066,"remaining_time":0.05037932442},
{"learn":[0.1708937058],"iteration":208,"passed_time":0.2506098593,"remaining_time":0.04916269966},
{"learn":[0.1700141247],"iteration":209,"passed_time":0.2517043512,"remaining_time":0.04794368594},
{"learn":[0.1691972659],"iteration":210,"passed_time":0.2527882656,"remaining_time":0.04672389743},
{"learn":[0.1685937368],"iteration":211,"passed_time":0.2539105447,"remaining_time":0.04551226744},
{"learn":[0.1677732651],"iteration":212,"passed_time":0.2550514944,"remaining_time":0.04430471968},
{"learn":[0.1670100139],"iteration":213,"passed_time":0.2567802669,"remaining_time":0.04319668041},
{"learn":[0.1660744594],"iteration":214,"passed_time":0.258028803,"remaining_time":0.04200468886},
{"learn":[0.1652914194],"iteration":215,"passed_time":0.2595304464,"remaining_time":0.04085201471},
{"learn":[0.1644777151],"iteration":216,"passed_time":0.2606047299,"remaining_time":0.03963113404},
{"learn":[0.1637495848],"iteration":217,"passed_time":0.2616770713,"remaining_time":0.03841131322},
{"learn":[0.1633483447],"iteration":218,"passed_time":0.2627214311,"remaining_time":0.03718887837},
{"learn":[0.1625077908],"iteration":219,"passed_time":0.2637464058,"remaining_time":0.03596541897},
{"learn":[0.1618746978],"iteration":220,"passed_time":0.2648649316,"remaining_time":0.03475603174},
{"learn":[0.1609473779],"iteration":221,"passed_time":0.2660155044,"remaining_time":0.03355150506},
{"learn":[0.1601432287],"iteration":222,"passed_time":0.2671761559,"remaining_time":0.03234868255},
{"learn":[0.1592498926],"iteration":223,"passed_time":0.2682693867,"remaining_time":0.03113841096},
{"learn":[0.1586579543],"iteration":224,"passed_time":0.2693896725,"remaining_time":0.02993218583},
{"learn":[0.1580628799],"iteration":225,"passed_time":0.2712389622,"remaining_time":0.02880413758},
{"learn":[0.1574932979],"iteration":226,"passed_time":0.2725833249,"remaining_time":0.02761857477},
{"learn":[0.1564857776],"iteration":227,"passed_time":0.2739205,"remaining_time":0.02643092544},
{"learn":[0.156036377],"iteration":228,"passed_time":0.2750795226,"remaining_time":0.02522563308},
{"learn":[0.1551432793],"iteration":229,"passed_time":0.2762125425,"remaining_time":0.02401848196},
{"learn":[0.1546350993],"iteration":230,"passed_time":0.2773048101,"remaining_time":0.02280862074},
{"learn":[0.1538393497],"iteration":231,"passed_time":0.2784639649,"remaining_time":0.02160496279},
{"learn":[0.1530091396],"iteration":232,"passed_time":0.2795099558,"remaining_time":0.02039343025},
{"learn":[0.1521063676],"iteration":233,"passed_time":0.2806062854,"remaining_time":0.01918675456},
{"learn":[0.151473834],"iteration":234,"passed_time":0.2816143772,"remaining_time":0.01797538578},
{"learn":[0.1508169908],"iteration":235,"passed_time":0.2826767343,"remaining_time":0.01676895882},
{"learn":[0.150300732],"iteration":236,"passed_time":0.2835582735,"remaining_time":0.01555382935},
{"learn":[0.1497846017],"iteration":237,"passed_time":0.2856494508,"remaining_time":0.01440249332},
{"learn":[0.1491354245],"iteration":238,"passed_time":0.2868222309,"remaining_time":0.01320102318},
{"learn":[0.1482712489],"iteration":239,"passed_time":0.287921316,"remaining_time":0.0119967215},
{"learn":[0.1476999246],"iteration":240,"passed_time":0.2892188732,"remaining_time":0.01080070481},
{"learn":[0.1473027193],"iteration":241,"passed_time":0.2904234959,"remaining_time":0.009600776722},
{"learn":[0.1462699358],"iteration":242,"passed_time":0.2915371462,"remaining_time":0.008398189397},
{"learn":[0.1455795582],"iteration":243,"passed_time":0.2926174474,"remaining_time":0.007195511001},
{"learn":[0.1448290165],"iteration":244,"passed_time":0.2936399988,"remaining_time":0.005992653037},
{"learn":[0.1442341896],"iteration":245,"passed_time":0.2947149612,"remaining_time":0.00479211319},
{"learn":[0.1434599436],"iteration":246,"passed_time":0.295916985,"remaining_time":0.003594133421},
{"learn":[0.1429894704],"iteration":247,"passed_time":0.2977161303,"remaining_time":0.002400936535},
{"learn":[0.1422256506],"iteration":248,"passed_time":0.2988773318,"remaining_time":0.001200310569},
{"learn":[0.1416438543],"iteration":249,"passed_time":0.2999743937,"remaining_time":0}
]}